aptexp-0.2.3.dist-info/DESCRIPTION.rst
aptexp-0.2.3.dist-info/METADATA
aptexp-0.2.3.dist-info/RECORD
aptexp-0.2.3.dist-info/WHEEL
aptexp-0.2.3.dist-info/entry_points.txt
aptexp-0.2.3.dist-info/metadata.json
aptexp-0.2.3.dist-info/top_level.txt
aptexp-0.2.3.dist-info/zip-safe
aptexpy/__init__.py
aptexpy/aptexp.py
aptexpy/config.py
aptexpy/generate.py
aptexpy/query.py
