Metadata-Version: 2.0
Name: aptexp
Version: 0.2.3
Summary: A tiny tools to export simple xls file from mongodb based on Python
Home-page: UNKNOWN
Author: Duolk
Author-email: 1229125444@qq.com
License: Beihang
Keywords: python mongodb xls
Platform: UNKNOWN
Requires-Dist: xlrd
Requires-Dist: xlwt
Requires-Dist: xlutils
